sorteo/__init__.py
sorteo/main.py
sorteo-0.1.0.dist-info/LICENSE
sorteo-0.1.0.dist-info/METADATA
sorteo-0.1.0.dist-info/WHEEL
sorteo-0.1.0.dist-info/entry_points.txt
sorteo-0.1.0.dist-info/top_level.txt
sorteo-0.1.0.dist-info/RECORD
