Metadata-Version: 2.1
Name: sorteo
Version: 0.1.0
Summary: Sorteos usando los asistentes de un evento de Meetup
Home-page: https://sorteo.readthedocs.io
Author: Santos Gallegos
Author-email: santos_g@outlook.com
License: MIT
Project-URL: Documentation, https://sorteo.readthedocs.io
Project-URL: Source Code, https://github.com/stsewd/sorteo
Project-URL: Bug Tracker, https://github.com/stsewd/sorteo/issues
Platform: UNKNOWN
Requires-Python: >=3.6
Requires-Dist: tortilla (<0.6.0,>=0.5.0)
Provides-Extra: docs
Requires-Dist: sphinx; extra == 'docs'
Requires-Dist: sphinx-rtd-theme; extra == 'docs'
Requires-Dist: sphinx-argparse; extra == 'docs'
Requires-Dist: sphinx-autobuild; extra == 'docs'
